src/__init__.py
src/config/__init__.py
src/config/config.py
src/core/__init__.py
src/core/earnings_fetcher.py
src/core/financial_analyzer.py
src/core/policy_analyzer.py
src/core/sentiment_analyzer.py
src/data/__init__.py
src/data/cache_manager.py
src/data/cache_warmer.py
src/data/cached_data_fetcher.py
src/data/data_fetcher.py
src/data/enhanced_policy_fetcher.py
src/ui/__init__.py
src/ui/base_components.py
src/ui/charts.py
src/ui/dashboard_background_processor.py
src/ui/dashboard_data_manager.py
src/ui/dashboard_ui_updater.py
src/ui/data_tables.py
src/ui/market_components.py
src/ui/panel_components.py
src/ui/textual_dashboard.py
src/ui/tree_view_components.py
stockholm_finance-1.1.15.dist-info/licenses/LICENSE
stockholm_finance-1.1.15.dist-info/METADATA
stockholm_finance-1.1.15.dist-info/WHEEL
stockholm_finance-1.1.15.dist-info/entry_points.txt
stockholm_finance-1.1.15.dist-info/top_level.txt
stockholm_finance-1.1.15.dist-info/RECORD
