Metadata-Version: 2.4
Name: stockholm-finance
Version: 1.1.15
Summary: Advanced financial sentiment analysis tool with policy impact assessment
Author-email: Andrew <contact@andrewfarney.net>
Maintainer-email: Andrew <contact@andrewfarney.net>
License: MIT License
Project-URL: Homepage, https://github.com/aykaym/stockholm
Project-URL: Documentation, https://github.com/aykaym/stockholm/blob/main/README.md
Project-URL: Repository, https://github.com/aykaym/stockholm
Project-URL: Bug Tracker, https://github.com/aykaym/stockholm/issues
Project-URL: Changelog, https://github.com/aykaym/stockholm/blob/main/CHANGELOG.md
Keywords: finance,sentiment-analysis,nlp,market-analysis,policy-analysis,trading,investment
Classifier: Development Status :: 4 - Beta
Classifier: Intended Audience :: Financial and Insurance Industry
Classifier: Intended Audience :: Developers
Classifier: Topic :: Office/Business :: Financial :: Investment
Classifier: Topic :: Scientific/Engineering :: Artificial Intelligence
Classifier: Topic :: Text Processing :: Linguistic
Classifier: License :: OSI Approved :: MIT License
Classifier: Programming Language :: Python :: 3
Classifier: Programming Language :: Python :: 3.8
Classifier: Programming Language :: Python :: 3.9
Classifier: Programming Language :: Python :: 3.10
Classifier: Programming Language :: Python :: 3.11
Classifier: Programming Language :: Python :: 3.12
Classifier: Operating System :: OS Independent
Requires-Python: >=3.8
License-File: LICENSE
Requires-Dist: textblob>=0.17.1
Requires-Dist: yfinance>=0.2.18
Requires-Dist: requests>=2.31.0
Requires-Dist: numpy>=1.24.0
Requires-Dist: feedparser>=6.0.10
Requires-Dist: textual>=0.41.0
Requires-Dist: rich>=13.5.0
Requires-Dist: textual_plotext>=0.2.0
Requires-Dist: python-dateutil>=2.8.2
Requires-Dist: pytz>=2023.3
Provides-Extra: dev
Requires-Dist: pytest>=7.0.0; extra == "dev"
Requires-Dist: pytest-cov>=4.0.0; extra == "dev"
Requires-Dist: pytest-xdist>=3.0.0; extra == "dev"
Requires-Dist: black>=23.0.0; extra == "dev"
Requires-Dist: isort>=5.12.0; extra == "dev"
Requires-Dist: flake8>=6.0.0; extra == "dev"
Requires-Dist: mypy>=1.0.0; extra == "dev"
Requires-Dist: bandit>=1.7.0; extra == "dev"
Requires-Dist: safety>=2.3.0; extra == "dev"
Provides-Extra: performance
Requires-Dist: pytest-benchmark>=4.0.0; extra == "performance"
Requires-Dist: memory-profiler>=0.60.0; extra == "performance"
Requires-Dist: psutil>=5.9.0; extra == "performance"
Provides-Extra: docs
Requires-Dist: mkdocs>=1.5.0; extra == "docs"
Requires-Dist: mkdocs-material>=9.4.0; extra == "docs"
Requires-Dist: mkdocs-git-revision-date-localized-plugin>=1.2.0; extra == "docs"
Requires-Dist: mkdocs-git-committers-plugin-2>=1.2.0; extra == "docs"
Requires-Dist: mkdocs-minify-plugin>=0.7.0; extra == "docs"
Requires-Dist: mkdocs-gen-files>=0.5.0; extra == "docs"
Requires-Dist: mkdocs-literate-nav>=0.6.0; extra == "docs"
Requires-Dist: mkdocs-section-index>=0.3.0; extra == "docs"
Requires-Dist: pymdown-extensions>=10.0.0; extra == "docs"
Dynamic: license-file
